cassia_rag/__init__.py
cassia_rag/core.py
cassia_rag-0.1.4.dist-info/METADATA
cassia_rag-0.1.4.dist-info/WHEEL
cassia_rag-0.1.4.dist-info/top_level.txt
cassia_rag-0.1.4.dist-info/RECORD
